jaganathanj/__init__.py
jaganathanj/__main__.py
jaganathanj/cli.py
jaganathanj-1.0.18.dist-info/licenses/LICENSE
jaganathanj-1.0.18.dist-info/METADATA
jaganathanj-1.0.18.dist-info/WHEEL
jaganathanj-1.0.18.dist-info/entry_points.txt
jaganathanj-1.0.18.dist-info/top_level.txt
jaganathanj-1.0.18.dist-info/RECORD
