Metadata-Version: 2.4
Name: jaganathanj
Version: 1.0.18
Summary: Personal portfolio and CLI identity package for Jaganathan J, instead of countless resumes
Home-page: https://jaganathan-j-portfolio.vercel.app/
Author: Jaganathan J
Author-email: Jaganathan J <jaganathanjjds@gmail.com>
License: MIT License
Project-URL: Homepage, https://jaganathan-j-portfolio.vercel.app/
Project-URL: Repository, https://github.com/J-Jaganathan/jaganathanj
Project-URL: Issues, https://github.com/J-Jaganathan/jaganathanj-package/issues
Project-URL: Documentation, https://github.com/J-Jaganathan/jaganathanj#readme
Project-URL: Changelog, https://github.com/J-Jaganathan/jaganathanj/releases
Project-URL: LinkedIn, https://linkedin.com/in/jaganathan-jn
Project-URL: YouTube, https://youtube.com/@Tech_CrafterX
Project-URL: Bug Reports, https://github.com/J-Jaganathan/jaganathanj/issues
Project-URL: Source Code, https://github.com/J-Jaganathan/jaganathanj
Keywords: resume,portfolio,personal-brand,cv,developer,student,cli,terminal,identity,professional,career,hacker-aesthetic
Classifier: Development Status :: 5 - Production/Stable
Classifier: Intended Audience :: Developers
Classifier: Intended Audience :: End Users/Desktop
Classifier: Topic :: Software Development :: Libraries :: Python Modules
Classifier: Topic :: System :: System Shells
Classifier: Topic :: Terminals
Classifier: Topic :: Documentation
Classifier: License :: OSI Approved :: MIT License
Classifier: Programming Language :: Python :: 3
Classifier: Programming Language :: Python :: 3.6
Classifier: Programming Language :: Python :: 3.7
Classifier: Programming Language :: Python :: 3.8
Classifier: Programming Language :: Python :: 3.9
Classifier: Programming Language :: Python :: 3.10
Classifier: Programming Language :: Python :: 3.11
Classifier: Programming Language :: Python :: 3.12
Classifier: Operating System :: OS Independent
Classifier: Environment :: Console
Classifier: Natural Language :: English
Requires-Python: >=3.6
License-File: LICENSE
Dynamic: author
Dynamic: home-page
Dynamic: license-file
Dynamic: requires-python
